tap_api/__init__.py
tap_api/common/__init__.py
tap_api/common/filters.py
tap_api/v2/__init__.py
tap_api/v2/client.py
tap_api/v2/endpoints/__init__.py
tap_api/v2/endpoints/campaign/__init__.py
tap_api/v2/endpoints/campaign/actor.py
tap_api/v2/endpoints/campaign/campaign.py
tap_api/v2/endpoints/campaign/campaign_family.py
tap_api/v2/endpoints/campaign/campaign_id.py
tap_api/v2/endpoints/campaign/campaign_info.py
tap_api/v2/endpoints/campaign/campaign_member.py
tap_api/v2/endpoints/campaign/campaign_metadata.py
tap_api/v2/endpoints/campaign/campaign_summary.py
tap_api/v2/endpoints/campaign/ids.py
tap_api/v2/endpoints/campaign/malware.py
tap_api/v2/endpoints/campaign/technique.py
tap_api/v2/endpoints/forensics/__init__.py
tap_api/v2/endpoints/forensics/aggregate.py
tap_api/v2/endpoints/forensics/evidence.py
tap_api/v2/endpoints/forensics/evidence_types.py
tap_api/v2/endpoints/forensics/forensics.py
tap_api/v2/endpoints/forensics/platform.py
tap_api/v2/endpoints/forensics/report.py
tap_api/v2/endpoints/people/__init__.py
tap_api/v2/endpoints/people/identity.py
tap_api/v2/endpoints/people/people.py
tap_api/v2/endpoints/people/threat_family.py
tap_api/v2/endpoints/people/threat_statistics.py
tap_api/v2/endpoints/people/user.py
tap_api/v2/endpoints/people/vap.py
tap_api/v2/endpoints/people/vap_summary.py
tap_api/v2/endpoints/siem/__init__.py
tap_api/v2/endpoints/siem/actor.py
tap_api/v2/endpoints/siem/all.py
tap_api/v2/endpoints/siem/blocked.py
tap_api/v2/endpoints/siem/click_event.py
tap_api/v2/endpoints/siem/clicks.py
tap_api/v2/endpoints/siem/delivered.py
tap_api/v2/endpoints/siem/issues.py
tap_api/v2/endpoints/siem/message_event.py
tap_api/v2/endpoints/siem/message_parts.py
tap_api/v2/endpoints/siem/messages.py
tap_api/v2/endpoints/siem/permitted.py
tap_api/v2/endpoints/siem/siem.py
tap_api/v2/endpoints/siem/siem_data.py
tap_api/v2/endpoints/siem/threats_info_map.py
tap_api/v2/endpoints/threats/__init__.py
tap_api/v2/endpoints/threats/actor.py
tap_api-1.1.1.dist-info/LICENSE
tap_api-1.1.1.dist-info/METADATA
tap_api-1.1.1.dist-info/WHEEL
tap_api-1.1.1.dist-info/top_level.txt
tap_api-1.1.1.dist-info/RECORD
