Metadata-Version: 2.2
Name: tap-api
Version: 1.1.1
Summary: Targeted Attack Protection Python API Package
License: MIT
Project-URL: repository, https://github.com/pfptcommunity/tap-api-python
Project-URL: homepage, https://help.proofpoint.com/Threat_Insight_Dashboard/API_Documentation
Requires-Python: >3.9
License-File: LICENSE
Requires-Dist: requests
Requires-Dist: pysocks
